{
  "track": {
    "name": "Skin",
    "url": "https://open.spotify.com/track/4uqfL7UKwWPF1bpZok6zGs",
    "artists": [
      {
        "name": "Hans Williams",
        "url": "https://open.spotify.com/artist/3SEkDN2vusR7CIyehzfJaj"
      }
    ],
    "played_at": "2026-03-16T22:56:40.103Z"
  },
  "fetched_at": "2026-03-16T23:48:10Z",
  "context": {
    "type": "playlist",
    "name": "floating",
    "url": "https://open.spotify.com/playlist/607PxSGVeYpWMFiqtNgW6f?sessionId=1773705600002&mode=enhanced"
  }
}